beeline/__init__.py
beeline/aiotrace.py
beeline/internal.py
beeline/middleware/__init__.py
beeline/middleware/awslambda/__init__.py
beeline/middleware/awslambda/test_awslambda.py
beeline/middleware/bottle/__init__.py
beeline/middleware/bottle/test_bottle.py
beeline/middleware/django/__init__.py
beeline/middleware/django/test_django.py
beeline/middleware/flask/__init__.py
beeline/middleware/flask/test_flask.py
beeline/middleware/werkzeug/__init__.py
beeline/middleware/werkzeug/test_werkzeug.py
beeline/middleware/wsgi.py
beeline/patch/__init__.py
beeline/patch/jinja2.py
beeline/patch/requests.py
beeline/patch/test_jinja2.py
beeline/patch/test_requests.py
beeline/patch/test_urllib.py
beeline/patch/tornado.py
beeline/patch/urllib.py
beeline/propagation/__init__.py
beeline/propagation/default.py
beeline/propagation/honeycomb.py
beeline/propagation/test_honeycomb.py
beeline/propagation/test_propagation.py
beeline/propagation/test_w3c.py
beeline/propagation/w3c.py
beeline/test_async.py
beeline/test_beeline.py
beeline/test_internal.py
beeline/test_suite.py
beeline/test_trace.py
beeline/trace.py
beeline/version.py
honeycomb_beeline-3.5.2.dist-info/entry_points.txt
honeycomb_beeline-3.5.2.dist-info/WHEEL
honeycomb_beeline-3.5.2.dist-info/METADATA
honeycomb_beeline-3.5.2.dist-info/LICENSE
honeycomb_beeline-3.5.2.dist-info/RECORD
