Metadata-Version: 2.1
Name: honeycomb-beeline
Version: 3.5.2
Summary: Honeycomb library for easy instrumentation
Home-page: https://github.com/honeycombio/beeline-python
License: Apache-2.0
Author: Honeycomb.io
Author-email: feedback@honeycomb.io
Requires-Python: >=3.7,<4
Classifier: License :: OSI Approved :: Apache Software License
Classifier: Programming Language :: Python :: 3
Classifier: Programming Language :: Python :: 3.7
Classifier: Programming Language :: Python :: 3.8
Classifier: Programming Language :: Python :: 3.9
Classifier: Programming Language :: Python :: 3.10
Classifier: Programming Language :: Python :: 3.11
Requires-Dist: libhoney (>=2.3.0,<3.0.0)
Requires-Dist: wrapt (>=1.12.1,<2.0.0)
Project-URL: Repository, https://github.com/honeycombio/beeline-python
